README
setup.py
oosheet/__init__.py
oosheet/columns.py
oosheet.egg-info/PKG-INFO
oosheet.egg-info/SOURCES.txt
oosheet.egg-info/dependency_links.txt
oosheet.egg-info/entry_points.txt
oosheet.egg-info/top_level.txt