Metadata-Version: 1.0
Name: oosheet
Version: 1.2
Summary: OpenOffice.org Spreadsheet scripting library
Home-page: http://oosheet.hacklab.com.br/
Author: Luis Fagundes
Author-email: lhfagundes@hacklab.com.br
License: The MIT License
Platform: UNKNOWN
Classifier: Intended Audience :: Developers
Classifier: Natural Language :: English
Classifier: Operating System :: OS Independent
Classifier: Programming Language :: Python
Classifier: Topic :: Office/Business :: Financial :: Spreadsheet
